Workbook

Sheet Cover
B1: RSM Impact Investing Case Competition 2025
B3: Table of Contents
B5: Outputs
B6: Inputs
B7: Model

Sheet Outputs
B1: Outputs
B3: Project Economics (Unlevered)
B6: Model Drivers Set To | E6: 2
B8: Metric | E8: Base | G8: Best | I8: Worst
B10: Unlevered IRR | E10: =E24 -> 0.15763643 | G10: =E23 -> 0.19776594 | I10: =E25 -> 0.11510612
B11: NPV @ 8,3% | E11: =F24 -> 3691.4991 | G11: =F23 -> 6131.7114 | I11: =F25 -> 1442.8589
B12: Payback | E12: =G24 -> 10 | G12: =G23 -> 9 | I12: =G25 -> 11
B13: EBITDA margin | E13: =I24 -> 0.24078389 | G13: =I23 -> 0.29766379 | I13: =I25 -> 0.18345986
B16: Stegra delivers 16 % unlevered IRR and 3557 m NPV @ 8 %, proving strong project economics before leverage.
B19: Scenario Summary
E21: Unlev IRR | F21: NPV | G21: Payback | H21: Gross M | I21: EBITDA M | J21: Equity IRR | K21: Min DSCR | L21: LLCR
E22: =Model!$F$191 -> 0.15763643 | F22: =Model!F193 -> 3691.4991 | G22: =Model!$F$195 -> 10 | H22: =Model!H93 -> 0.32639732 | I22: =Model!H98 -> 0.24078389 | J22: =Model!F305 -> 0.24344134 | K22: =Model!H261 -> 1.7492788 | L22: =Model!H267 -> 1.5304267
B23: Best Case | D23: 1 | E23: 0.19776594 | F23: 6131.7114 | G23: 9 | H23: 0.38200671 | I23: 0.29766379 | J23: 0.31591262 | K23: 2.2079643 | L23: 1.9641054
B24: Base Case | D24: 2 | E24: 0.15763643 | F24: 3691.4991 | G24: 10 | H24: 0.32639732 | I24: 0.24078389 | J24: 0.24344134 | K24: 1.7492788 | L24: 1.5304267
B25: Worst Case | D25: 3 | E25: 0.11510612 | F25: 1442.8589 | G25: 11 | H25: 0.27027233 | I25: 0.18345986 | J25: 0.16723693 | K25: 1.3250551 | L25: 1.1307804
B28: Best Case - It assumes a 30% green premium, 75% offtake coverage, and renewable power at €45/MWh due to optimized PPA sourcing. Pellet cost falls to €90/t.
B29: Base Case - It assumes a 25% green premium, 70% offtake coverage under long-term contracts, and renewable power at €50/MWh under the PPA. Pellet costs are set at €100/t, and inflation at 2%.
B30: Worst Case - Conservative stress conditions to test resilience. It assumes a 20% green premium, 65% offtake coverage (greater spot exposure), electricity cost €60/MWh, and pellet cost €110/t.
B33: Capital Structuring
B35: Model Drivers Set To | E35: 2
B38: Metric | E38: Project IRR | G38: Equity IRR | I38: Min DSCR | K38: Comment | M38: Debt | N38: Equity
E39: =Model!F191 -> 0.15763643 | G39: =Model!F305 -> 0.24344134 | I39: =Model!H261 -> 1.7492788
B40: Single Financial Close | D40: 1 | E40: 0.13305476 | F40: 0 | G40: 0.20486776 | H40: 0 | I40: 1.6108537 | K40: High debt, early risk | M40: =Inputs!$K$35 -> 0.6 | N40: =Inputs!$K$36 -> 0.4
B41: Two Phased | D41: 2 | E41: 0.15763643 | F41: 0 | G41: 0.24344134 | H41: 0 | I41: 1.7492788 | K41: Balanced risk return | M41: =Inputs!$K$35 -> 0.6 | N41: =Inputs!$K$36 -> 0.4
X44: 2025 | Y44: =X44+1 -> 2026 | Z44: =Y44+1 -> 2027 | AA44: =Z44+1 -> 2028 | AB44: =AA44+1 -> 2029
W45: Single Financial Close | X45: =Inputs!F143 -> 5500 | Y45: =Inputs!G143 -> 0 | Z45: =Inputs!H143 -> 0 | AA45: =Inputs!I143 -> 0 | AB45: =Inputs!J143 -> 0
W46: Two Phased | X46: =Inputs!F144 -> 1500 | Y46: =Inputs!G144 -> 1500 | Z46: =Inputs!H144 -> 1000 | AA46: =Inputs!I144 -> 1000 | AB46: =Inputs!J144 -> 500
B55: Phased financing reduces execution risk, smooths cash flows, and raises equity IRR (+5 pp) while keeping DSCR > 1.6× — the optimal for Stegra.
B57: Financing & Bankability
B60: Metric - Base Scenario | E60: Value | G60: Target / Comment
B62: Total Funding | E62: =Inputs!F40 -> 5500 | G62: 70% debt, 30% equity
B63: Operating Life | E63: 20 years
B64: Debt Tenor | E64: 20 | G64: For two-phased credit arrangements
B65: Debt, Rate | E65: =Inputs!F151 -> 0.06 | G65: EIB / EAC Standard
B66: WACC | E66: =Inputs!L79 -> 0.083159675 | G66: Projected Stegra's cost of capital
B68: DSCR | E68: =$M$24 -> 0 | G68: >= 1,3x Covenant 1
B69: LLCR | E69: =$N$24 -> 0 | G69: >= 1,3x Covenant 2
B70: Max Total Debt / EBITDA | E70: =AC75 -> 2.379205 | G70: <= 4,0x from Phase 2 Operations. Optional Covenant | Z70: =Model!H6 -> 2027 | AA70: =Model!I6 -> 2028 | AB70: =Model!J6 -> 2029 | AC70: =Model!K6 -> 2030 | AD70: =Model!L6 -> 2031 | AE70: =Model!M6 -> 2032 | AF70: =Model!N6 -> 2033 | AG70: =Model!O6 -> 2034 | ... AS70: =Model!AA6 -> 2046
B72: Equity IRR | E72: =J24 -> 0.24344134 | G72: > 15% PE hurdle rate | W72: EBITDA | Z72: =Model!H$97 -> 442.4232 | AA72: =Model!I$97 -> 560.26738 | AB72: =Model!J$97 -> 682.64835 | AC72: =Model!K$97 -> 1198.6209 | AD72: =Model!L$97 -> 1334.6645 | AE72: =Model!M$97 -> 1475.124 | AF72: =Model!N$97 -> 1500.893 | AG72: =Model!O$97 -> 1523.3019 | ... AS72: =Model!AA$97 -> 1728.7868
B73: Payback for Investors | E73: =L24 -> 1.5304267 | G73: Follows PE fund lifecycle | W73: Total Debt | Z73: =Model!H249 -> 1710 | AA73: =Model!I249 -> 1620 | AB73: =Model!J249 -> 3030 | AC73: =Model!K249 -> 2851.7647 | AD73: =Model!L249 -> 2673.5294 | AE73: =Model!M249 -> 2495.2941 | AF73: =Model!N249 -> 2317.0588 | AG73: =Model!O249 -> 2138.8235 | ... AS73: =Model!AA249 -> -1.9895197e-13
W75: Total Debt / EBITDA | Z75: =Z73/Z72 -> 3.8650776 | AA75: =AA73/AA72 -> 2.8914766 | AB75: =AB73/AB72 -> 4.4385957 | AC75: =AC73/AC72 -> 2.379205 | AD75: =AD73/AD72 -> 2.0031471 | AE75: =AE73/AE72 -> 1.6915826 | AF75: =AF73/AF72 -> 1.5437869 | AG75: =AG73/AG72 -> 1.4040707 | ... AR75: =AR73/AR72 -> 0.10404476 | AS75: 0.01
W76: Debt Service Coverage Ratio | Z76: =Model!H259 -> 1.7492788 | AA76: =Model!I259 -> 2.1445745 | AB76: =Model!J259 -> 2.693018 | AC76: =Model!K259 -> 2.1632267 | AD76: =Model!L259 -> 2.9112374 | AE76: =Model!M259 -> 3.3119764 | AF76: =Model!N259 -> 3.5966294 | AG76: =Model!O259 -> 3.7718959 | ... AS76: =Model!AA259 -> 7.1260515
B87: DSCR 1.7× and LLCR 1.5× confirm lender comfort — project is bankable under a 70/30 structure.
B92: Sensitivity & Breakeven Analysis
B94: WACC | C94: =Inputs!$L$79 -> 0.083159675
B96: WACC Sensitivity – NPV vs. Discount Rate | G96: Tornado Chart | U96: Variable | W96: Value | X96: +10% | Y96: -10% | Z96: IRR (- 10%) | AA96: IRR (+ 10%) | AB96: Change -pp
D98: NPV | U98: Green Premium | W98: =Inputs!H97 -> 0.25
B99: WACC | C99: 0.06 | D99: =XNPV(C99,Model!$F$186:$AA$186,Model!$F$185:$AA$185) -> 5832.4503 | U99: Offtake Coverage | W99: =Inputs!H111 -> 0.75
C100: 0.07 | D100: =XNPV(C100,Model!$F$186:$AA$186,Model!$F$185:$AA$185) -> 4821.066 | U100: Electricity cost | W100: =Inputs!H118 -> 54.121608
C101: =C94 -> 0.083159675 | D101: =XNPV(C101,Model!$F$186:$AA$186,Model!$F$185:$AA$185) -> 3691.4991 | U101: Pellet cost | W101: =Inputs!H125 -> 108.24322
C102: 0.09 | D102: =XNPV(C102,Model!$F$186:$AA$186,Model!$F$185:$AA$185) -> 3181.3219
C103: 0.1 | D103: =XNPV(C103,Model!$F$186:$AA$186,Model!$F$185:$AA$185) -> 2516.3873
B107: Breakeven Analysis
B135: Financing & Bankability Dashboard
D138: Model Drivers Set To | F138: 2 | L138: All figures in USD thousands unless stated
D141: Main Outputs 1 | L141: Selected Inputs
F143: Enterprise | G143: Equity | H143: Equity
F144: Value | G144: Value | H144: Per Share | L144: Terminal Growth Rate | O144: =Inputs!#REF! -> #REF!
F145: =Model!#REF! -> #REF! | L145: WACC | O145: =Inputs!#REF! -> #REF!
D146: Best Case | E146: 1 | F146: #REF! | G146: =F146-$O$146 -> #REF! | H146: =G146/$O$147 -> #REF! | L146: Net Debt | N146: =CONCATENATE("(End of ",Model!$H$6,")") -> (End of 2027) | O146: =Inputs!#REF! -> #REF!
D147: Base Case | E147: 2 | F147: #REF! | G147: =F147-$O$146 -> #REF! | H147: =G147/$O$147 -> #REF! | L147: Shares Outstanding | N147: (FD 000) | O147: =Inputs!#REF! -> #REF!
D148: Worst Case | E148: 3 | F148: #REF! | G148: =F148-$O$146 -> #REF! | H148: =G148/$O$147 -> #REF! | L148: Current Stock Price | N148: (US$/sh) | O148: =Inputs!#REF! -> #REF!
D152: Enterprise Value 1 | L152: Equity Value per Share
D154: Terminal Growth Rate | L154: Terminal Growth Rate
C155: =Model!#REF! -> #REF! | D155: =E155-0.005 -> #REF! | E155: =F155-0.005 -> #REF! | F155: =Inputs!#REF! -> #REF! | G155: =F155+0.005 -> #REF! | H155: =G155+0.005 -> #REF! | L155: =D155 -> #REF! | M155: =E155 -> #REF! | N155: =F155 -> #REF! | O155: =G155 -> #REF! | P155: =H155 -> #REF!
B156: WACC | C156: =C157-0.01 -> #REF! | D156: #REF! | E156: #REF! | F156: #REF! | G156: #REF! | H156: #REF! | J156: WACC | K156: =C156 -> #REF! | L156: =D169/$O$147 -> #REF! | M156: =E169/$O$147 -> #REF! | N156: =F169/$O$147 -> #REF! | O156: =G169/$O$147 -> #REF! | P156: =H169/$O$147 -> #REF!
C157: =C158-0.01 -> #REF! | D157: #REF! | E157: #REF! | F157: #REF! | G157: #REF! | H157: #REF! | K157: =C157 -> #REF! | L157: =D170/$O$147 -> #REF! | M157: =E170/$O$147 -> #REF! | N157: =F170/$O$147 -> #REF! | O157: =G170/$O$147 -> #REF! | P157: =H170/$O$147 -> #REF!
C158: =Inputs!#REF! -> #REF! | D158: #REF! | E158: #REF! | F158: #REF! | G158: #REF! | H158: #REF! | K158: =C158 -> #REF! | L158: =D171/$O$147 -> #REF! | M158: =E171/$O$147 -> #REF! | N158: =F171/$O$147 -> #REF! | O158: =G171/$O$147 -> #REF! | P158: =H171/$O$147 -> #REF!
C159: =C158+0.01 -> #REF! | D159: #REF! | E159: #REF! | F159: #REF! | G159: #REF! | H159: #REF! | K159: =C159 -> #REF! | L159: =D172/$O$147 -> #REF! | M159: =E172/$O$147 -> #REF! | N159: =F172/$O$147 -> #REF! | O159: =G172/$O$147 -> #REF! | P159: =H172/$O$147 -> #REF!
C160: =C159+0.01 -> #REF! | D160: #REF! | E160: #REF! | F160: #REF! | G160: #REF! | H160: #REF! | K160: =C160 -> #REF! | L160: =D173/$O$147 -> #REF! | M160: =E173/$O$147 -> #REF! | N160: =F173/$O$147 -> #REF! | O160: =G173/$O$147 -> #REF! | P160: =H173/$O$147 -> #REF!
D165: Equity Value | L165: Premium (Discount) to Stock Price
D167: Terminal Growth Rate | L167: Terminal Growth Rate
D168: =D155 -> #REF! | E168: =E155 -> #REF! | F168: =F155 -> #REF! | G168: =G155 -> #REF! | H168: =H155 -> #REF! | L168: =D168 -> #REF! | M168: =E168 -> #REF! | N168: =F168 -> #REF! | O168: =G168 -> #REF! | P168: =H168 -> #REF!
B169: WACC | C169: =C156 -> #REF! | D169: =D156-$O$146 -> #REF! | E169: =E156-$O$146 -> #REF! | F169: =F156-$O$146 -> #REF! | G169: =G156-$O$146 -> #REF! | H169: =H156-$O$146 -> #REF! | J169: WACC | K169: =C169 -> #REF! | L169: =L156/$O$148-1 -> #REF! | M169: =M156/$O$148-1 -> #REF! | N169: =N156/$O$148-1 -> #REF! | O169: =O156/$O$148-1 -> #REF! | P169: =P156/$O$148-1 -> #REF!
C170: =C157 -> #REF! | D170: =D157-$O$146 -> #REF! | E170: =E157-$O$146 -> #REF! | F170: =F157-$O$146 -> #REF! | G170: =G157-$O$146 -> #REF! | H170: =H157-$O$146 -> #REF! | K170: =C170 -> #REF! | L170: =L157/$O$148-1 -> #REF! | M170: =M157/$O$148-1 -> #REF! | N170: =N157/$O$148-1 -> #REF! | O170: =O157/$O$148-1 -> #REF! | P170: =P157/$O$148-1 -> #REF!
C171: =C158 -> #REF! | D171: =D158-$O$146 -> #REF! | E171: =E158-$O$146 -> #REF! | F171: =F158-$O$146 -> #REF! | G171: =G158-$O$146 -> #REF! | H171: =H158-$O$146 -> #REF! | K171: =C171 -> #REF! | L171: =L158/$O$148-1 -> #REF! | M171: =M158/$O$148-1 -> #REF! | N171: =N158/$O$148-1 -> #REF! | O171: =O158/$O$148-1 -> #REF! | P171: =P158/$O$148-1 -> #REF!
C172: =C159 -> #REF! | D172: =D159-$O$146 -> #REF! | E172: =E159-$O$146 -> #REF! | F172: =F159-$O$146 -> #REF! | G172: =G159-$O$146 -> #REF! | H172: =H159-$O$146 -> #REF! | K172: =C172 -> #REF! | L172: =L159/$O$148-1 -> #REF! | M172: =M159/$O$148-1 -> #REF! | N172: =N159/$O$148-1 -> #REF! | O172: =O159/$O$148-1 -> #REF! | P172: =P159/$O$148-1 -> #REF!
C173: =C160 -> #REF! | D173: =D160-$O$146 -> #REF! | E173: =E160-$O$146 -> #REF! | F173: =F160-$O$146 -> #REF! | G173: =G160-$O$146 -> #REF! | H173: =H160-$O$146 -> #REF! | K173: =C173 -> #REF! | L173: =L160/$O$148-1 -> #REF! | M173: =M160/$O$148-1 -> #REF! | N173: =N160/$O$148-1 -> #REF! | O173: =O160/$O$148-1 -> #REF! | P173: =P160/$O$148-1 -> #REF!
P175: These tables require the workbook calculation to be set to automatic to update.
B179: Dashboard: Multiple Method
D182: Model Drivers Set To | L182: All figures in USD thousands unless stated
D185: Main Outputs 1 | L185: Selected Inputs
F187: Enterprise | G187: Equity | H187: Equity
F188: Value | G188: Value | H188: Per Share | L188: Terminal Multiple | O188: =+Inputs!#REF! -> #REF!
F189: =Model!#REF! -> #REF! | L189: WACC | O189: =Inputs!#REF! -> #REF!
D190: =D146 -> Best Case | E190: 1 | F190: #REF! | G190: =F190-$O$190 -> #REF! | H190: =+G190/$O$191 -> #REF! | L190: Net Debt | N190: =N146 -> (End of 2027) | O190: =Inputs!#REF! -> #REF!
D191: =D147 -> Base Case | E191: 2 | F191: #REF! | G191: =F191-$O$190 -> #REF! | H191: =+G191/$O$191 -> #REF! | L191: Shares Outstanding | N191: (FD 000) | O191: =Inputs!#REF! -> #REF!
D192: =D148 -> Worst Case | E192: 3 | F192: #REF! | G192: =F192-$O$190 -> #REF! | H192: =+G192/$O$191 -> #REF! | L192: Current Stock Price | N192: (US$/sh) | O192: =Inputs!#REF! -> #REF!
D196: Enterprise Value 1 | L196: Equity Value per Share
D198: Terminal Multiple | L198: Terminal Multiple
C199: =Model!#REF! -> #REF! | D199: =E199-0.5 -> #REF! | E199: =F199-0.5 -> #REF! | F199: =+Inputs!#REF! -> #REF! | G199: =+F199+0.5 -> #REF! | H199: =+G199+0.5 -> #REF! | L199: =D199 -> #REF! | M199: =E199 -> #REF! | N199: =F199 -> #REF! | O199: =G199 -> #REF! | P199: =H199 -> #REF!
B200: WACC | C200: =C201-0.01 -> #REF! | D200: #REF! | E200: #REF! | F200: #REF! | G200: #REF! | H200: #REF! | J200: WACC | K200: =C200 -> #REF! | L200: =D213/$O$191 -> #REF! | M200: =E213/$O$191 -> #REF! | N200: =F213/$O$191 -> #REF! | O200: =G213/$O$191 -> #REF! | P200: =H213/$O$191 -> #REF!
C201: =C202-0.01 -> #REF! | D201: #REF! | E201: #REF! | F201: #REF! | G201: #REF! | H201: #REF! | K201: =C201 -> #REF! | L201: =D214/$O$191 -> #REF! | M201: =E214/$O$191 -> #REF! | N201: =F214/$O$191 -> #REF! | O201: =G214/$O$191 -> #REF! | P201: =H214/$O$191 -> #REF!
C202: =Inputs!#REF! -> #REF! | D202: #REF! | E202: #REF! | F202: #REF! | G202: #REF! | H202: #REF! | K202: =C202 -> #REF! | L202: =D215/$O$191 -> #REF! | M202: =E215/$O$191 -> #REF! | N202: =F215/$O$191 -> #REF! | O202: =G215/$O$191 -> #REF! | P202: =H215/$O$191 -> #REF!
C203: =C202+0.01 -> #REF! | D203: #REF! | E203: #REF! | F203: #REF! | G203: #REF! | H203: #REF! | K203: =C203 -> #REF! | L203: =D216/$O$191 -> #REF! | M203: =E216/$O$191 -> #REF! | N203: =F216/$O$191 -> #REF! | O203: =G216/$O$191 -> #REF! | P203: =H216/$O$191 -> #REF!
C204: =C203+0.01 -> #REF! | D204: #REF! | E204: #REF! | F204: #REF! | G204: #REF! | H204: #REF! | K204: =C204 -> #REF! | L204: =D217/$O$191 -> #REF! | M204: =E217/$O$191 -> #REF! | N204: =F217/$O$191 -> #REF! | O204: =G217/$O$191 -> #REF! | P204: =H217/$O$191 -> #REF!
D209: Equity Value | L209: Premium (Discount) to Stock Price
D211: Terminal Multiple | L211: Terminal Multiple
D212: =D199 -> #REF! | E212: =E199 -> #REF! | F212: =F199 -> #REF! | G212: =G199 -> #REF! | H212: =H199 -> #REF! | L212: =D212 -> #REF! | M212: =E212 -> #REF! | N212: =F212 -> #REF! | O212: =G212 -> #REF! | P212: =H212 -> #REF!
B213: WACC | C213: =C200 -> #REF! | D213: =D200-$O$190 -> #REF! | E213: =E200-$O$190 -> #REF! | F213: =F200-$O$190 -> #REF! | G213: =G200-$O$190 -> #REF! | H213: =H200-$O$190 -> #REF! | J213: WACC | K213: =C213 -> #REF! | L213: =L200/$O$192-1 -> #REF! | M213: =M200/$O$192-1 -> #REF! | N213: =N200/$O$192-1 -> #REF! | O213: =O200/$O$192-1 -> #REF! | P213: =P200/$O$192-1 -> #REF!
...

Sheet Inputs
B1: Model Drivers
B3: Input
B5: Operations | H5: Cost
B7: Construction Start/End Year = 2025 / 2026 | F7: 2025 / 2026 | H7: Electricity Cost (EUR/MWh) | L7: 50
B8: Operations Start (COD) | F8: 2027 | H8: Electricity demand for 2.5 Mt of production TWh | L8: 7
B9: Phase 1 Plant Capacity 2027 - 2029 (Mtpa) | F9: 2.5 | H9: Pellet Cost (EUR/t) | L9: 100
B10: Phase 2 Plant Capacity > 2030 (Mtpa) | F10: 5 | H10: Pellet Intensity, for 1tonne steel* | L10: 1.5
B11: Ramp Years to 100% = 3 (60% in 2027, 85% in 2028, 100% in 2029) | H11: Scrap Usage (tonnes/tonne steel)** | L11: 0.31
H12: Scrap Metal Price*** | L12: 385
B13: Revenue | H13: Consumables & Alloys *** | L13: 130
H14: Other (Logistics, Utilties) | L14: 95
B15: European HRC average 2023 (€/t) | F15: 800 | H15: FTE Operational Phase 1 | L15: 1500
B16: Tax rate, corporate Sweden | F16: 0.206 | H16: Direct Labor | L16: 750
H17: Indirect Labor | L17: 750
H18: FTE Operational Phase 2 Increase | L18: 0.4
H19: Direct Labor cost, (€/t) **** | L19: 49
H20: Labor cost average (EUR)**** | L20: 75000
H21: Other SG&A, % of Revenue | L21: 0.035
H22: R&D, % of Revenue | L22: 0.02
L24: It takes approximately 1.5 tons of DR-grade iron ore pellets to produce 1 ton of crude steel *
L25: 20-30% blend in EAF; common for green steel to maintain quality **
L26: 2025 average data; https://www.steelorbis.com/steel-market/scrap.htm ***
L27: Eurostat 2024 “Hourly Labour Costs in Manufacturing, Sweden; https://www.scb.se/en/finding-statistics/statistics-by-subject-area/labour-market/wages-salaries-and-labour-costs/ ****
B30: Sources & Uses
B32: All figures in EUR millions unless stated
B34: Uses of Cash | E34: % | F34: Amount | H34: Sources of Cash | K34: % | L34: Amount
B35: Construction and Operations | F35: 5500 | H35: Debt Term Loan | K35: 0.6 | L35: =K35*L40 -> 3300
B36: If Two-Phased Construction: | H36: Equity Value | K36: 0.4 | L36: =K36*L40 -> 2200
B37: Phase 1: | E37: =F37/F35 -> 0.54545455 | F37: 3000
B38: Phase 2: | E38: =F38/F35 -> 0.45454545 | F38: 2500
B40: Total Uses: | E40: 1 | F40: =F35+F39 -> 5500 | H40: Total Uses | K40: =K35+K36 -> 1 | L40: =F40 -> 5500
B43: Weighted Average Cost of Capital
B45: All figures in EUR millions unless stated
H47: Average | I47: Debt/ | J47: Debt/ | K47: Levered | L47: Unlevered
B48: Peers Group | D48: Region | F48: Debt | G48: Equity | H48: Tax Rate | I48: Equity | J48: Capital | K48: Beta | L48: Beta
B50: SSAB AB | D50: Europe | F50: 1200 | G50: 5000 | H50: 0.205 | I50: =F50/G50 -> 0.24 | J50: =F50/(F50+G50) -> 0.19354839 | K50: 1.15 | L50: =K50/(1+(1-H50)*I50) -> 0.96573732
B51: Outokumpu Oyj | D51: Europe | F51: 800 | G51: 2300 | H51: 0.182 | I51: =F51/G51 -> 0.34782609 | J51: =F51/(F51+G51) -> 0.25806452 | K51: 1.42 | L51: =K51/(1+(1-H51)*I51) -> 1.1054698
B52: Salzgitter AG | D52: Europe | F52: 2100 | G52: 3400 | H52: 0.281 | I52: =F52/G52 -> 0.61764706 | J52: =F52/(F52+G52) -> 0.38181818 | K52: 1.28 | L52: =K52/(1+(1-H52)*I52) -> 0.88637243
B53: ThyssenKrupp AG | D53: Europe | F53: 4500 | G53: 6800 | H53: 0.253 | I53: =F53/G53 -> 0.66176471 | J53: =F53/(F53+G53) -> 0.39823009 | K53: 1.55 | L53: =K53/(1+(1-H53)*I53) -> 1.0372484
G56: Average | H56: =AVERAGE(H50:H54) -> 0.23025 | I56: =AVERAGE(I50:I54) -> 0.46680946 | J56: =AVERAGE(J50:J54) -> 0.30791529 | K56: =AVERAGE(K50:K54) -> 1.35 | L56: =AVERAGE(L50:L54) -> 0.998707
B58: Risk Premium for Equity | H58: Cost of Equity
B60: Market Risk Premium | F60: 0.055 | H60: Risk Free Rate | L60: 0.028
B61: Average Unlevered Beta | F61: =$L$56 -> 0.998707 | H61: Equity Risk Premium | L61: =F63 -> 0.12034919
B62: Levered Beta | F62: =F61*(1+(1-L68)*F72) -> 2.188167 | H62: Country Risk Premium | L62: 0
B63: Equity Risk Premium | F63: =F60*F62 -> 0.12034919 | H63: Cost of Equity | L63: =SUM(L60:L62) -> 0.14834919
B65: Capital Structure | H65: Cost of Debt
E67: Current | F67: Target | H67: Pre-Tax Cost of Debt | L67: 0.05
B68: Total Debt | D68: =$L$35 -> 3300 | E68: =K35 -> 0.6 | F68: =K35 -> 0.6 | H68: Tax Rate | L68: =$F$16 -> 0.206
B69: Market Capitalization | D69: =$L$36 -> 2200 | E69: =1-E68 -> 0.4 | F69: =1-F68 -> 0.4 | H69: After-Tax Cost of Debt | L69: =L67*(1-L68) -> 0.0397
B70: Total Capitalization | D70: =SUM(D68:D69) -> 5500 | E70: =SUM(E68:E69) -> 1 | F70: =SUM(F68:F69) -> 1
B72: Debt / Equity | E72: =E68/E69 -> 1.5 | F72: =F68/F69 -> 1.5 | H72: Weighted Average Cost of Capital
B74: Peer Tax-rate from financial statements | K74: Weight | L74: Cost
B75: Levered beta is on 5-year monthly data from Yahoo Finance | H75: Debt Capital | K75: =F68 -> 0.6 | L75: =L69 -> 0.0397
B76: Unlevered Beta = Levered Beta / (1 + (1 - Tax Rate) × Debt-to-Equity) | H76: Equity Capital | K76: =F69 -> 0.4 | L76: =L63 -> 0.14834919
B77: Levered Beta = Unlevered Beta x (1 + (1 - Tax rate) x (Debt-to-Equity))
B78: Risk-Free Rate (Rf) Sweden 20Y
B79: Equity Risk Premium (ERP) 5.5% Damodaran Europe 2025 / AQR | H79: Weighted Average Cost of Capital | L79: =SUMPRODUCT(K75:K76,L75:L76) -> 0.083159675
B82: Scenario Drivers
B84: All figures in EUR millions unless stated | F84: 2025 | G84: =F84+1 -> 2026 | H84: =G84+1 -> 2027 | I84: =H84+1 -> 2028 | J84: =I84+1 -> 2029 | K84: =J84+1 -> 2030 | L84: =K84+1 -> 2031 | M84: =L84+1 -> 2032 | N84: =M84+1 -> 2033 | ... AA84: =Z84+1 -> 2046
B86: Driver Switch | D86: =Outputs!$E$6 -> 2
B88: Inflation Rate | F88: 0.02 | G88: 0.02 | H88: 0.02 | I88: 0.02 | J88: 0.02 | K88: 0.019 | L88: 0.019 | M88: 0.019 | N88: 0.019 | O88: 0.018 | P88: 0.018 | Q88: 0.018 | R88: 0.017 | S88: 0.016 | T88: 0.016 | U88: 0.016 | V88: 0.016 | W88: 0.016 | X88: 0.016 | Y88: 0.016 | Z88: 0.016 | AA88: 0.016
B91: Base Steel Price | D91: EUR / t | F91: =800*(1+0.02)^2 -> 832.32 | G91: =F91*(1+G88) -> 848.9664 | H91: =G91*(1+H88) -> 865.94573 | I91: =H91*(1+I88) -> 883.26464 | J91: =I91*(1+J88) -> 900.92994 | K91: =J91*(1+K88) -> 918.0476 | L91: =K91*(1+L88) -> 935.49051 | M91: =L91*(1+M88) -> 953.26483 | N91: =M91*(1+N88) -> 971.37686 | ... AA91: =Z91*(1+AA88) -> 1202.2517
B92: * 800 EUR 2023 in case
B94: Green Premium, Offtake | F94: {=INDEX(F96:F98,$D$86)} -> 0 | G94: {=INDEX(G96:G98,$D$86)} -> 0 | H94: {=INDEX(H96:H98,$D$86)} -> 0.25 | I94: {=INDEX(I96:I98,$D$86)} -> 0.25 | J94: {=INDEX(J96:J98,$D$86)} -> 0.25 | K94: {=INDEX(K96:K98,$D$86)} -> 0.25 | L94: {=INDEX(L96:L98,$D$86)} -> 0.25 | M94: {=INDEX(M96:M98,$D$86)} -> 0.25 | ... AA94: {=INDEX(AA96:AA98,$D$86)} -> 0.25
B96: =Outputs!$D$146 -> Best Case | D96: % | F96: 0 | G96: 0 | H96: 0.3 | I96: 0.3 | J96: 0.3 | K96: 0.3 | L96: 0.3 | M96: 0.3 | N96: 0.3 | O96: 0.3 | P96: 0.3 | Q96: 0.3 | R96: 0.3 | S96: 0.3 | T96: 0.3 | U96: 0.3 | V96: 0.3 | W96: 0.3 | X96: 0.3 | Y96: 0.3 | Z96: 0.3 | AA96: 0.3
B97: =Outputs!$D$147 -> Base Case | D97: % | F97: 0 | G97: 0 | H97: 0.25 | I97: 0.25 | J97: 0.25 | K97: 0.25 | L97: 0.25 | M97: 0.25 | N97: 0.25 | O97: 0.25 | P97: 0.25 | Q97: 0.25 | R97: 0.25 | S97: 0.25 | T97: 0.25 | U97: 0.25 | V97: 0.25 | W97: 0.25 | X97: 0.25 | Y97: 0.25 | Z97: 0.25 | AA97: 0.25
B98: =Outputs!$D$148 -> Worst Case | D98: % | F98: 0 | G98: 0 | H98: 0.204 | I98: 0.204 | J98: 0.204 | K98: 0.204 | L98: 0.204 | M98: 0.204 | N98: 0.204 | O98: 0.204 | P98: 0.204 | Q98: 0.204 | R98: 0.204 | S98: 0.204 | T98: 0.204 | U98: 0.204 | V98: 0.204 | W98: 0.204 | X98: 0.204 | Y98: 0.204 | Z98: 0.204 | AA98: 0.204
B101: Green Premium, Spot | F101: {=INDEX(F103:F105,$D$86)} -> 0 | G101: {=INDEX(G103:G105,$D$86)} -> 0 | H101: {=INDEX(H103:H105,$D$86)} -> 0.1 | I101: {=INDEX(I103:I105,$D$86)} -> 0.1 | J101: {=INDEX(J103:J105,$D$86)} -> 0.1 | K101: {=INDEX(K103:K105,$D$86)} -> 0.1 | L101: {=INDEX(L103:L105,$D$86)} -> 0.1 | M101: {=INDEX(M103:M105,$D$86)} -> 0.1 | ... AA101: {=INDEX(AA103:AA105,$D$86)} -> 0.1
B103: =$B$96 -> Best Case | D103: % | F103: 0 | G103: 0 | H103: 0.125 | I103: 0.125 | J103: 0.125 | K103: 0.125 | L103: 0.125 | M103: 0.125 | N103: 0.125 | O103: 0.125 | P103: 0.125 | Q103: 0.125 | R103: 0.125 | S103: 0.125 | T103: 0.125 | U103: 0.125 | V103: 0.125 | W103: 0.125 | X103: 0.125 | Y103: 0.125 | Z103: 0.125 | AA103: 0.125
B104: =$B$97 -> Base Case | D104: % | F104: 0 | G104: 0 | H104: 0.1 | I104: 0.1 | J104: 0.1 | K104: 0.1 | L104: 0.1 | M104: 0.1 | N104: 0.1 | O104: 0.1 | P104: 0.1 | Q104: 0.1 | R104: 0.1 | S104: 0.1 | T104: 0.1 | U104: 0.1 | V104: 0.1 | W104: 0.1 | X104: 0.1 | Y104: 0.1 | Z104: 0.1 | AA104: 0.1
B105: =$B$98 -> Worst Case | D105: % | F105: 0 | G105: 0 | H105: 0.08 | I105: 0.08 | J105: 0.08 | K105: 0.08 | L105: 0.08 | M105: 0.08 | N105: 0.08 | O105: 0.08 | P105: 0.08 | Q105: 0.08 | R105: 0.08 | S105: 0.08 | T105: 0.08 | U105: 0.08 | V105: 0.08 | W105: 0.08 | X105: 0.08 | Y105: 0.08 | Z105: 0.08 | AA105: 0.08
B108: Offtake Coverage | F108: {=INDEX(F110:F112,$D$86)} -> 0 | G108: {=INDEX(G110:G112,$D$86)} -> 0 | H108: {=INDEX(H110:H112,$D$86)} -> 0.75 | I108: {=INDEX(I110:I112,$D$86)} -> 0.75 | J108: {=INDEX(J110:J112,$D$86)} -> 0.75 | K108: {=INDEX(K110:K112,$D$86)} -> 0.75 | L108: {=INDEX(L110:L112,$D$86)} -> 0.75 | M108: {=INDEX(M110:M112,$D$86)} -> 0.75 | ... AA108: {=INDEX(AA110:AA112,$D$86)} -> 0.75
B110: =$B$96 -> Best Case | D110: % | F110: 0 | G110: 0 | H110: 0.8 | I110: 0.8 | J110: 0.8 | K110: 0.8 | L110: 0.8 | M110: 0.8 | N110: 0.8 | O110: 0.8 | P110: 0.8 | Q110: 0.8 | R110: 0.8 | S110: 0.8 | T110: 0.8 | U110: 0.8 | V110: 0.8 | W110: 0.8 | X110: 0.8 | Y110: 0.8 | Z110: 0.8 | AA110: 0.8
B111: =$B$97 -> Base Case | D111: % | F111: 0 | G111: 0 | H111: 0.75 | I111: 0.75 | J111: 0.75 | K111: 0.75 | L111: 0.75 | M111: 0.75 | N111: 0.75 | O111: 0.75 | P111: 0.75 | Q111: 0.75 | R111: 0.75 | S111: 0.75 | T111: 0.75 | U111: 0.75 | V111: 0.75 | W111: 0.75 | X111: 0.75 | Y111: 0.75 | Z111: 0.75 | AA111: 0.75
B112: =$B$98 -> Worst Case | D112: % | F112: 0 | G112: 0 | H112: 0.7 | I112: 0.7 | J112: 0.7 | K112: 0.7 | L112: 0.7 | M112: 0.7 | N112: 0.7 | O112: 0.7 | P112: 0.7 | Q112: 0.7 | R112: 0.7 | S112: 0.7 | T112: 0.7 | U112: 0.7 | V112: 0.7 | W112: 0.7 | X112: 0.7 | Y112: 0.7 | Z112: 0.7 | AA112: 0.7
B115: Electricity cost | F115: {=INDEX(F117:F119,$D$86)} -> 52.02 | G115: {=INDEX(G117:G119,$D$86)} -> 53.0604 | H115: {=INDEX(H117:H119,$D$86)} -> 54.121608 | I115: {=INDEX(I117:I119,$D$86)} -> 55.20404 | J115: {=INDEX(J117:J119,$D$86)} -> 56.308121 | K115: {=INDEX(K117:K119,$D$86)} -> 57.377975 | L115: {=INDEX(L117:L119,$D$86)} -> 58.468157 | M115: {=INDEX(M117:M119,$D$86)} -> 59.579052 | ... AA115: {=INDEX(AA117:AA119,$D$86)} -> 75.140733
B117: =$B$96 -> Best Case | D117: EUR / MWh | F117: 47 | G117: =F117*(1+G88) -> 47.94 | H117: =G117*(1+H88) -> 48.8988 | I117: =H117*(1+I88) -> 49.876776 | J117: =I117*(1+J88) -> 50.874312 | K117: =J117*(1+K88) -> 51.840923 | L117: =K117*(1+L88) -> 52.825901 | M117: =L117*(1+M88) -> 53.829593 | N117: =M117*(1+N88) -> 54.852355 | ... AA117: =Z117*(1+AA88) -> 67.889551
B118: =$B$97 -> Base Case | D118: EUR / MWh | F118: =50*(1+0.02)^2 -> 52.02 | G118: =F118*(1+G88) -> 53.0604 | H118: =G118*(1+H88) -> 54.121608 | I118: =H118*(1+I88) -> 55.20404 | J118: =I118*(1+J88) -> 56.308121 | K118: =J118*(1+K88) -> 57.377975 | L118: =K118*(1+L88) -> 58.468157 | M118: =L118*(1+M88) -> 59.579052 | N118: =M118*(1+N88) -> 60.711054 | ... AA118: =Z118*(1+AA88) -> 75.140733
B119: =$B$98 -> Worst Case | D119: EUR / MWh | F119: 57 | G119: =F119*(1+G88) -> 58.14 | H119: =G119*(1+H88) -> 59.3028 | I119: =H119*(1+I88) -> 60.488856 | J119: =I119*(1+J88) -> 61.698633 | K119: =J119*(1+K88) -> 62.870907 | L119: =K119*(1+L88) -> 64.065454 | M119: =L119*(1+M88) -> 65.282698 | N119: =M119*(1+N88) -> 66.523069 | ... AA119: =Z119*(1+AA88) -> 82.334137
B120: * 50 EUR end of 2022
B122: Iron-ore pellet | F122: {=INDEX(F124:F126,$D$86)} -> 104.04 | G122: {=INDEX(G124:G126,$D$86)} -> 106.1208 | H122: {=INDEX(H124:H126,$D$86)} -> 108.24322 | I122: {=INDEX(I124:I126,$D$86)} -> 110.40808 | J122: {=INDEX(J124:J126,$D$86)} -> 112.61624 | K122: {=INDEX(K124:K126,$D$86)} -> 114.75595 | L122: {=INDEX(L124:L126,$D$86)} -> 116.93631 | M122: {=INDEX(M124:M126,$D$86)} -> 119.1581 | ... AA122: {=INDEX(AA124:AA126,$D$86)} -> 150.28147
B124: =$B$96 -> Best Case | D124: EUR / t | F124: 94 | G124: =F124*(1+G88) -> 95.88 | H124: =G124*(1+H88) -> 97.7976 | I124: =H124*(1+I88) -> 99.753552 | J124: =I124*(1+J88) -> 101.74862 | K124: =J124*(1+K88) -> 103.68185 | L124: =K124*(1+L88) -> 105.6518 | M124: =L124*(1+M88) -> 107.65919 | N124: =M124*(1+N88) -> 109.70471 | ... AA124: =Z124*(1+AA88) -> 135.7791
B125: =$B$97 -> Base Case | D125: EUR / t | F125: =100*(1+0.02)^2 -> 104.04 | G125: =F125*(1+G88) -> 106.1208 | H125: =G125*(1+H88) -> 108.24322 | I125: =H125*(1+I88) -> 110.40808 | J125: =I125*(1+J88) -> 112.61624 | K125: =J125*(1+K88) -> 114.75595 | L125: =K125*(1+L88) -> 116.93631 | M125: =L125*(1+M88) -> 119.1581 | N125: =M125*(1+N88) -> 121.42211 | ... AA125: =Z125*(1+AA88) -> 150.28147
B126: =$B$98 -> Worst Case | D126: EUR / t | F126: 114 | G126: =F126*(1+G88) -> 116.28 | H126: =G126*(1+H88) -> 118.6056 | I126: =H126*(1+I88) -> 120.97771 | J126: =I126*(1+J88) -> 123.39727 | K126: =J126*(1+K88) -> 125.74181 | L126: =K126*(1+L88) -> 128.13091 | M126: =L126*(1+M88) -> 130.5654 | N126: =M126*(1+N88) -> 133.04614 | ... AA126: =Z126*(1+AA88) -> 164.66827
B127: * 100 EUR end of 2022
B129: Working Capital*
B130: Accounts Receivable | D130: (Days) | F130: - | G130: - | H130: 40 | I130: 40 | J130: 40 | K130: 40 | L130: 40 | M130: 40 | N130: 40 | O130: 40 | P130: 40 | Q130: 40 | R130: 40 | S130: 40 | T130: 40 | U130: 40 | V130: 40 | W130: 40 | X130: 40 | Y130: 40 | Z130: 40 | AA130: 40
B131: Inventory | D131: (Days) | F131: - | G131: - | H131: 50 | I131: 50 | J131: 50 | K131: 50 | L131: 50 | M131: 50 | N131: 50 | O131: 50 | P131: 50 | Q131: 50 | R131: 50 | S131: 50 | T131: 50 | U131: 50 | V131: 50 | W131: 50 | X131: 50 | Y131: 50 | Z131: 50 | AA131: 50
B132: Accounts Payable | D132: (Days) | F132: - | G132: - | H132: 60 | I132: 60 | J132: 60 | K132: 60 | L132: 60 | M132: 60 | N132: 60 | O132: 60 | P132: 60 | Q132: 60 | R132: 60 | S132: 60 | T132: 60 | U132: 60 | V132: 60 | W132: 60 | X132: 60 | Y132: 60 | Z132: 60 | AA132: 60
B134: * We have assumed working capital amounts aligned to the industry benchmarks (United States Steel Corporation).
B137: Construction Capex and Financing Drivers
B139: Driver Switch | D139: =Outputs!E35 -> 2 | F139: 2025 | G139: =F139+1 -> 2026 | H139: =G139+1 -> 2027 | I139: =H139+1 -> 2028 | J139: =I139+1 -> 2029 | K139: =J139+1 -> 2030 | L139: =K139+1 -> 2031 | M139: =L139+1 -> 2032 | N139: =M139+1 -> 2033 | ... AA139: =Z139+1 -> 2046
B141: Construction Capex | F141: {=INDEX(F143:F144,$D$139)} -> 1500 | G141: {=INDEX(G143:G144,$D$139)} -> 1500 | H141: {=INDEX(H143:H144,$D$139)} -> 1000 | I141: {=INDEX(I143:I144,$D$139)} -> 1000 | J141: {=INDEX(J143:J144,$D$139)} -> 500 | K141: {=INDEX(K143:K144,$D$139)} -> 0 | L141: {=INDEX(L143:L144,$D$139)} -> 0 | M141: {=INDEX(M143:M144,$D$139)} -> 0 | ... AA141: {=INDEX(AA143:AA144,$D$139)} -> 0
B143: Single Financial Close | F143: 5500 | G143: 0 | H143: 0 | I143: 0 | J143: 0 | K143: 0 | L143: 0 | M143: 0 | N143: 0 | O143: 0 | P143: 0 | Q143: 0 | R143: 0 | S143: 0 | T143: 0 | U143: 0 | V143: 0 | W143: 0 | X143: 0 | Y143: 0 | Z143: 0 | AA143: 0
B144: Two Phased | F144: 1500 | G144: 1500 | H144: 1000 | I144: 1000 | J144: 500 | K144: 0 | L144: 0 | M144: 0 | N144: 0 | O144: 0 | P144: 0 | Q144: 0 | R144: 0 | S144: 0 | T144: 0 | U144: 0 | V144: 0 | W144: 0 | X144: 0 | Y144: 0 | Z144: 0 | AA144: 0
F147: Debt rate
B148: Financing | F148: {=INDEX(F150:F151,$D$139)} -> 0.06
B150: Single Close | F150: 0.05
B151: Two Phased | F151: 0.06

Sheet Model
B1: Model
B3: Revenue Schedule
B5: All figures in EUR millions unless stated | H5: Operations - Phase 1 | K5: Operations - Phase 2
B6: {=CONCATENATE("Model Drivers: ",INDEX(Inputs!$B$96:$B$98,Inputs!$D$86)," & ",INDEX(Inputs!$B$143:$B$144,Inputs!$D$139)," Financing")} -> Model Drivers: Base Case & Two Phased Financing | F6: 2025 | G6: 2026 | H6: =Inputs!$F$8 -> 2027 | I6: =H6+1 -> 2028 | J6: =I6+1 -> 2029 | K6: =J6+1 -> 2030 | L6: =K6+1 -> 2031 | M6: =L6+1 -> 2032 | N6: =M6+1 -> 2033 | O6: =N6+1 -> 2034 | P6: =O6+1 -> 2035 | ... AA6: =Z6+1 -> 2046
B8: PRODUCTION CAPACITY
B9: Phase 1 Starting Capacity | D9: (Mtpa/Year) | H9: =Inputs!$F$9 -> 2.5 | I9: =Inputs!$F$9 -> 2.5 | J9: =Inputs!$F$9 -> 2.5 | K9: =Inputs!$F$9 -> 2.5 | L9: =Inputs!$F$9 -> 2.5 | M9: =Inputs!$F$9 -> 2.5 | N9: =Inputs!$F$9 -> 2.5 | O9: =Inputs!$F$9 -> 2.5 | ... AA9: =Inputs!$F$9 -> 2.5
B10: Phase 2 Additional Capacity | D10: (Mtpa/Year) | H10: 0 | I10: 0 | J10: 0 | K10: 2.5 | L10: 2.5 | M10: 2.5 | N10: 2.5 | O10: 2.5 | P10: 2.5 | Q10: 2.5 | R10: 2.5 | S10: 2.5 | T10: 2.5 | U10: 2.5 | V10: 2.5 | W10: 2.5 | X10: 2.5 | Y10: 2.5 | Z10: 2.5 | AA10: 2.5
B11: Total Capacity | D11: (Mtpa/Year) | H11: =SUM(H9:H10) -> 2.5 | I11: =SUM(I9:I10) -> 2.5 | J11: 0 | K11: =SUM(K9:K10) -> 5 | L11: =SUM(L9:L10) -> 5 | M11: =SUM(M9:M10) -> 5 | N11: =SUM(N9:N10) -> 5 | O11: =SUM(O9:O10) -> 5 | P11: =SUM(P9:P10) -> 5 | Q11: =SUM(Q9:Q10) -> 5 | R11: =SUM(R9:R10) -> 5 | ... AA11: =SUM(AA9:AA10) -> 5
B13: UTILISATION
B14: Utilisation Phase 1 | D14: ( % of Capacity) | H14: 0.7 | I14: 0.85 | J14: 1 | K14: 1 | L14: 1 | M14: 1 | N14: 1 | O14: 1 | P14: 1 | Q14: 1 | R14: 1 | S14: 1 | T14: 1 | U14: 1 | V14: 1 | W14: 1 | X14: 1 | Y14: 1 | Z14: 1 | AA14: 1
B15: Utilisation Phase 2 | D15: ( % of Capacity) | H15: 0 | I15: 0 | J15: 0 | K15: 0.7 | L15: 0.85 | M15: 1 | N15: 1 | O15: 1 | P15: 1 | Q15: 1 | R15: 1 | S15: 1 | T15: 1 | U15: 1 | V15: 1 | W15: 1 | X15: 1 | Y15: 1 | Z15: 1 | AA15: 1
B16: Total Plant Utilisation | H16: =AVERAGE(H14:H15) -> 0.35 | I16: =AVERAGE(I14:I15) -> 0.425 | J16: =AVERAGE(J14:J15) -> 0.5 | K16: =AVERAGE(K14:K15) -> 0.85 | L16: =AVERAGE(L14:L15) -> 0.925 | M16: =AVERAGE(M14:M15) -> 1 | N16: =AVERAGE(N14:N15) -> 1 | O16: =AVERAGE(O14:O15) -> 1 | ... AA16: =AVERAGE(AA14:AA15) -> 1
B18: OUTPUT
B19: Phase 1 Output | D19: (Mtpa/Year) | H19: =H9*H14 -> 1.75 | I19: =I9*I14 -> 2.125 | J19: =J9*J14 -> 2.5 | K19: =K9*K14 -> 2.5 | L19: =L9*L14 -> 2.5 | M19: =M9*M14 -> 2.5 | N19: =N9*N14 -> 2.5 | O19: =O9*O14 -> 2.5 | ... AA19: =AA9*AA14 -> 2.5
B20: Phase 2 Output | D20: (Mtpa/Year) | H20: =H10*H15 -> 0 | I20: =I10*I15 -> 0 | J20: =J10*J15 -> 0 | K20: =K10*K15 -> 1.75 | L20: =L10*L15 -> 2.125 | M20: =M10*M15 -> 2.5 | N20: =N10*N15 -> 2.5 | O20: =O10*O15 -> 2.5 | ... AA20: =AA10*AA15 -> 2.5
B21: Total Output | D21: (Mtpa/Year) | H21: =SUM(H19:H20) -> 1.75 | I21: =SUM(I19:I20) -> 2.125 | J21: =SUM(J19:J20) -> 2.5 | K21: =SUM(K19:K20) -> 4.25 | L21: =SUM(L19:L20) -> 4.625 | M21: =SUM(M19:M20) -> 5 | N21: =SUM(N19:N20) -> 5 | O21: =SUM(O19:O20) -> 5 | ... AA21: =SUM(AA19:AA20) -> 5
B23: PRICING
B24: Base Steel Price | D24: (EUR/Unit) | H24: =Inputs!H$91 -> 865.94573 | I24: =Inputs!I$91 -> 883.26464 | J24: =Inputs!J$91 -> 900.92994 | K24: =Inputs!K$91 -> 918.0476 | L24: =Inputs!L$91 -> 935.49051 | M24: =Inputs!M$91 -> 953.26483 | N24: =Inputs!N$91 -> 971.37686 | O24: =Inputs!O$91 -> 988.86164 | ... AA24: =Inputs!AA$91 -> 1202.2517
B25: Green Offtake Price | D25: =Inputs!$H$94 -> 0.25 | H25: =H$24*(1+Inputs!H$94) -> 1082.4322 | I25: =I$24*(1+Inputs!I$94) -> 1104.0808 | J25: =J$24*(1+Inputs!J$94) -> 1126.1624 | K25: =K$24*(1+Inputs!K$94) -> 1147.5595 | L25: =L$24*(1+Inputs!L$94) -> 1169.3631 | M25: =M$24*(1+Inputs!M$94) -> 1191.581 | N25: =N$24*(1+Inputs!N$94) -> 1214.2211 | O25: =O$24*(1+Inputs!O$94) -> 1236.0771 | ... AA25: =AA$24*(1+Inputs!AA$94) -> 1502.8147
B26: Green Spot Price | D26: =Inputs!$H$101 -> 0.1 | H26: =H$24*(1+Inputs!H$101) -> 952.5403 | I26: =I$24*(1+Inputs!I$101) -> 971.59111 | J26: =J$24*(1+Inputs!J$101) -> 991.02293 | K26: =K$24*(1+Inputs!K$101) -> 1009.8524 | L26: =L$24*(1+Inputs!L$101) -> 1029.0396 | M26: =M$24*(1+Inputs!M$101) -> 1048.5913 | N26: =N$24*(1+Inputs!N$101) -> 1068.5145 | O26: =O$24*(1+Inputs!O$101) -> 1087.7478 | ... AA26: =AA$24*(1+Inputs!AA$101) -> 1322.4769
B28: REVENUE
B29: Offtake Coverage Share | D29: % | H29: =Inputs!H$108 -> 0.75 | I29: =Inputs!I$108 -> 0.75 | J29: =Inputs!J$108 -> 0.75 | K29: =Inputs!K$108 -> 0.75 | L29: =Inputs!L$108 -> 0.75 | M29: =Inputs!M$108 -> 0.75 | N29: =Inputs!N$108 -> 0.75 | O29: =Inputs!O$108 -> 0.75 | ... AA29: =Inputs!AA$108 -> 0.75
B30: Spot Share | D30: % | H30: =1-H$29 -> 0.25 | I30: =1-I$29 -> 0.25 | J30: =1-J$29 -> 0.25 | K30: =1-K$29 -> 0.25 | L30: =1-L$29 -> 0.25 | M30: =1-M$29 -> 0.25 | N30: =1-N$29 -> 0.25 | O30: =1-O$29 -> 0.25 | ... AA30: =1-AA$29 -> 0.25
B32: Offtake Revenue | D32: (EUR, mio) | H32: =H21*H29*H25 -> 1420.6922 | I32: =I21*I29*I25 -> 1759.6288 | J32: =J21*J29*J25 -> 2111.5545 | K32: =K21*K29*K25 -> 3657.8459 | L32: =L21*L29*L25 -> 4056.2284 | M32: =M21*M29*M25 -> 4468.4289 | N32: =N21*N29*N25 -> 4553.329 | O32: =O21*O29*O25 -> 4635.289 | ... AA32: =AA21*AA29*AA25 -> 5635.555
B33: Spot Revenue | D33: (EUR, mio) | H33: =H21*H30*H26 -> 416.73638 | I33: =I21*I30*I26 -> 516.15778 | J33: =J21*J30*J26 -> 619.38933 | K33: =K21*K30*K26 -> 1072.9681 | L33: =L21*L30*L26 -> 1189.827 | M33: =M21*M30*M26 -> 1310.7391 | N33: =N21*N30*N26 -> 1335.6432 | O33: =O21*O30*O26 -> 1359.6848 | ... AA33: =AA21*AA30*AA26 -> 1653.0961
B34: Total Revenue | D34: (EUR, mio) | H34: =SUM(H32:H33) -> 1837.4286 | I34: =SUM(I32:I33) -> 2275.7866 | J34: =SUM(J32:J33) -> 2730.9439 | K34: =SUM(K32:K33) -> 4730.8141 | L34: =SUM(L32:L33) -> 5246.0554 | M34: =SUM(M32:M33) -> 5779.168 | N34: =SUM(N32:N33) -> 5888.9722 | O34: =SUM(O32:O33) -> 5994.9737 | ... AA34: =SUM(AA32:AA33) -> 7288.6511
B35: Total Revenue | D35: (EUR, mio) | H35: 1300.749 | I35: 1640.9449 | J35: 2081.9489 | K35: 3503.9199 | L35: 3889.3511 | M35: 4397.1275 | N35: 4474.0773 | O35: 4552.3736 | P35: 4620.6592 | Q35: 4689.9691 | R35: 4760.3187 | S35: 4831.7234 | T35: 4904.1993 | U35: 4977.7623 | V35: 5052.4287 | W35: 5128.2151 | X35: 5205.1384 | Y35: 5283.2154 | Z35: 5362.4637 | AA35: 5442.9006
B38: Cost Schedule
B40: All figures in EUR millions unless stated
B41: {=CONCATENATE("Model Drivers: ",INDEX(Inputs!$B$96:$B$98,Inputs!$D$86)," & ",INDEX(Inputs!$B$143:$B$144,Inputs!$D$139)," Financing")} -> Model Drivers: Base Case & Two Phased Financing | F41: 2025 | G41: 2026 | H41: =Inputs!$F$8 -> 2027 | I41: =H41+1 -> 2028 | J41: =I41+1 -> 2029 | K41: =J41+1 -> 2030 | L41: =K41+1 -> 2031 | M41: =L41+1 -> 2032 | N41: =M41+1 -> 2033 | O41: =N41+1 -> 2034 | P41: =O41+1 -> 2035 | ... AA41: =Z41+1 -> 2046
B43: Total Steel Output | D43: (Mtpa/Year) | H43: =H21 -> 1.75 | I43: =I21 -> 2.125 | J43: =J21 -> 2.5 | K43: =K21 -> 4.25 | L43: =L21 -> 4.625 | M43: =M21 -> 5 | N43: =N21 -> 5 | O43: =O21 -> 5 | ... AA43: =AA21 -> 5
B44: Pellets (Iron Ore) Usage | D44: (Mtpa/Year) | H44: =H43*Inputs!$L$10 -> 2.625 | I44: =I43*Inputs!$L$10 -> 3.1875 | J44: =J43*Inputs!$L$10 -> 3.75 | K44: =K43*Inputs!$L$10 -> 6.375 | L44: =L43*Inputs!$L$10 -> 6.9375 | M44: =M43*Inputs!$L$10 -> 7.5 | N44: =N43*Inputs!$L$10 -> 7.5 | O44: =O43*Inputs!$L$10 -> 7.5 | ... AA44: =AA43*Inputs!$L$10 -> 7.5
B45: Electricity Usage | D45: TWh | H45: =H43/2.5*Inputs!$L$8 -> 4.9 | I45: =I43/2.5*Inputs!$L$8 -> 5.95 | J45: =J43/2.5*Inputs!$L$8 -> 7 | K45: =K43/2.5*Inputs!$L$8 -> 11.9 | L45: =L43/2.5*Inputs!$L$8 -> 12.95 | M45: =M43/2.5*Inputs!$L$8 -> 14 | N45: =N43/2.5*Inputs!$L$8 -> 14 | O45: =O43/2.5*Inputs!$L$8 -> 14 | ... AA45: =AA43/2.5*Inputs!$L$8 -> 14
B46: Scrap Usage | D46: (Mtpa/Year) | H46: =H43*Inputs!$L$11 -> 0.5425 | I46: =I43*Inputs!$L$11 -> 0.65875 | J46: =J43*Inputs!$L$11 -> 0.775 | K46: =K43*Inputs!$L$11 -> 1.3175 | L46: =L43*Inputs!$L$11 -> 1.43375 | M46: =M43*Inputs!$L$11 -> 1.55 | N46: =N43*Inputs!$L$11 -> 1.55 | O46: =O43*Inputs!$L$11 -> 1.55 | ... AA46: =AA43*Inputs!$L$11 -> 1.55
B47: Inflation | D47: % | H47: =Inputs!$F$88 -> 0.02 | I47: =Inputs!$F$88 -> 0.02 | J47: =Inputs!$F$88 -> 0.02 | K47: =Inputs!$F$88 -> 0.02 | L47: =Inputs!$F$88 -> 0.02 | M47: =Inputs!$F$88 -> 0.02 | N47: =Inputs!$F$88 -> 0.02 | O47: =Inputs!$F$88 -> 0.02 | ... AA47: =Inputs!$F$88 -> 0.02
B50: COGS
B51: Pellets (Iron Ore) Price | D51: (EUR/t) | H51: =Inputs!H$122 -> 108.24322 | I51: =Inputs!I$122 -> 110.40808 | J51: =Inputs!J$122 -> 112.61624 | K51: =Inputs!K$122 -> 114.75595 | L51: =Inputs!L$122 -> 116.93631 | M51: =Inputs!M$122 -> 119.1581 | N51: =Inputs!N$122 -> 121.42211 | O51: =Inputs!O$122 -> 123.60771 | ... AA51: =Inputs!AA$122 -> 150.28147
B52: Electricity Price | D52: MWh | H52: =Inputs!H$115 -> 54.121608 | I52: =Inputs!I$115 -> 55.20404 | J52: =Inputs!J$115 -> 56.308121 | K52: =Inputs!K$115 -> 57.377975 | L52: =Inputs!L$115 -> 58.468157 | M52: =Inputs!M$115 -> 59.579052 | N52: =Inputs!N$115 -> 60.711054 | O52: =Inputs!O$115 -> 61.803853 | ... AA52: =Inputs!AA$115 -> 75.140733
B53: Scrap Metal Price | D53: (EUR/t) | H53: =Inputs!$L$12 -> 385 | I53: =H53*(1+I$47) -> 392.7 | J53: =I53*(1+J$47) -> 400.554 | K53: =J53*(1+K$47) -> 408.56508 | L53: =K53*(1+L$47) -> 416.73638 | M53: =L53*(1+M$47) -> 425.07111 | N53: =M53*(1+N$47) -> 433.57253 | O53: =N53*(1+O$47) -> 442.24398 | P53: =O53*(1+P$47) -> 451.08886 | ... AA53: =Z53*(1+AA$47) -> 560.8723
B54: Consumables & Alloys | D54: (EUR/t) | H54: =Inputs!$L$13 -> 130 | I54: =H54*(1+I$47) -> 132.6 | J54: =I54*(1+J$47) -> 135.252 | K54: =J54*(1+K$47) -> 137.95704 | L54: =K54*(1+L$47) -> 140.71618 | M54: =L54*(1+M$47) -> 143.5305 | N54: =M54*(1+N$47) -> 146.40111 | O54: =N54*(1+O$47) -> 149.32914 | P54: =O54*(1+P$47) -> 152.31572 | ... AA54: =Z54*(1+AA$47) -> 189.38545
B55: Direct Labor | D55: (EUR/t) | H55: =Inputs!$L$19 -> 49 | I55: =H55*(1+I$47) -> 49.98 | J55: =I55*(1+J$47) -> 50.9796 | K55: =J55*(1+K$47) -> 51.999192 | L55: =K55*(1+L$47) -> 53.039176 | M55: =L55*(1+M$47) -> 54.099959 | N55: =M55*(1+N$47) -> 55.181959 | O55: =N55*(1+O$47) -> 56.285598 | P55: =O55*(1+P$47) -> 57.41131 | ... AA55: =Z55*(1+AA$47) -> 71.383747
B56: Other (Logistics, Utilties) | D56: (EUR/t) | H56: =Inputs!$L$14 -> 95 | I56: =H56*(1+I$47) -> 96.9 | J56: =I56*(1+J$47) -> 98.838 | K56: =J56*(1+K$47) -> 100.81476 | L56: =K56*(1+L$47) -> 102.83106 | M56: =L56*(1+M$47) -> 104.88768 | N56: =M56*(1+N$47) -> 106.98543 | O56: =N56*(1+O$47) -> 109.12514 | P56: =O56*(1+P$47) -> 111.30764 | ... AA56: =Z56*(1+AA$47) -> 138.39706
B59: Pellets (Iron Ore) | D59: (EUR, mio) | G59: =H59/$H$34 -> 0.15463918 | H59: =H$51*H$44 -> 284.13844 | I59: =I$51*I$44 -> 351.92576 | J59: =J$51*J$44 -> 422.31091 | K59: =K$51*K$44 -> 731.56918 | L59: =L$51*L$44 -> 811.24568 | M59: =M$51*M$44 -> 893.68578 | N59: =N$51*N$44 -> 910.66581 | O59: =O$51*O$44 -> 927.05779 | ... AA59: =AA$51*AA$44 -> 1127.111
B60: Electricity | D60: (EUR, mio) | G60: =H60/$H$34 -> 0.1443299 | H60: =H$45*H$52 -> 265.19588 | I60: =I$45*I$52 -> 328.46404 | J60: =J$45*J$52 -> 394.15685 | K60: =K$45*K$52 -> 682.79791 | L60: =L$45*L$52 -> 757.16263 | M60: =M$45*M$52 -> 834.10672 | N60: =N$45*N$52 -> 849.95475 | O60: =O$45*O$52 -> 865.25394 | ... AA60: =AA$45*AA$52 -> 1051.9703
B61: Scrap Metal | D61: (EUR, mio) | G61: =H61/$H$34 -> 0.11367108 | H61: =H$46*H$53 -> 208.8625 | I61: =I$46*I$53 -> 258.69112 | J61: =J$46*J$53 -> 310.42935 | K61: =K$46*K$53 -> 538.28449 | L61: =L$46*L$53 -> 597.49579 | M61: =M$46*M$53 -> 658.86022 | N61: =N$46*N$53 -> 672.03742 | O61: =O$46*O$53 -> 685.47817 | ... AA61: =AA$46*AA$53 -> 869.35207
B62: Consumables & Alloys | D62: (EUR, mio) | G62: =H62/$H$34 -> 0.12381434 | H62: =H$54*H$43 -> 227.5 | I62: =I$54*I$43 -> 281.775 | J62: =J$54*J$43 -> 338.13 | K62: =K$54*K$43 -> 586.31742 | L62: =L$54*L$43 -> 650.81234 | M62: =M$54*M$43 -> 717.65252 | N62: =N$54*N$43 -> 732.00557 | O62: =O$54*O$43 -> 746.64568 | ... AA62: =AA$54*AA$43 -> 946.92726
B63: Direct Labor | D63: (EUR, mio) | G63: =H63/$H$34 -> 0.04666848 | H63: =H$55*H$43 -> 85.75 | I63: =I$55*I$43 -> 106.2075 | J63: =J$55*J$43 -> 127.449 | K63: =K$55*K$43 -> 220.99657 | L63: =L$55*L$43 -> 245.30619 | M63: =M$55*M$43 -> 270.4998 | N63: =N$55*N$43 -> 275.90979 | O63: =O$55*O$43 -> 281.42799 | ... AA63: =AA$55*AA$43 -> 356.91874
B64: Other (Logistics, Utilties) | D64: (EUR, mio) | G64: =H64/$H$34 -> 0.090479707 | H64: =H$43*H$56 -> 166.25 | I64: =I$43*I$56 -> 205.9125 | J64: =J$43*J$56 -> 247.095 | K64: =K$43*K$56 -> 428.46273 | L64: =L$43*L$56 -> 475.59363 | M64: =M$43*M$56 -> 524.43838 | N64: =N$43*N$56 -> 534.92715 | O64: =O$43*O$56 -> 545.62569 | ... AA64: =AA$43*AA$56 -> 691.98531
B66: Total COGS | D66: (EUR, mio) | H66: =SUM(H59:H64) -> 1237.6968 | I66: =SUM(I59:I64) -> 1532.9759 | J66: =SUM(J59:J64) -> 1839.5711 | K66: =SUM(K59:K64) -> 3188.4283 | L66: =SUM(L59:L64) -> 3537.6162 | M66: =SUM(M59:M64) -> 3899.2434 | N66: =SUM(N59:N64) -> 3975.5005 | O66: =SUM(O59:O64) -> 4051.4893 | ... AA66: =SUM(AA59:AA64) -> 5044.2646
B69: OPERATIONAL EXPENSES
B71: SG&A
B72: Indirect Labor (Admin, Sales, ESG) | D72: (EUR, mio) | H72: =Inputs!$L$17*Inputs!$L$20/1000000 -> 56.25 | I72: =H72*(1+I$47) -> 57.375 | J72: =I72*(1+J$47) -> 58.5225 | K72: =J72*(1+K$47)*(1+Inputs!$L$18) -> 83.57013 | L72: =K72*(1+L47) -> 85.241533 | M72: =L72*(1+M47) -> 86.946363 | N72: =M72*(1+N47) -> 88.685291 | O72: =N72*(1+O47) -> 90.458996 | P72: =O72*(1+P47) -> 92.268176 | Q72: =P72*(1+Q47) -> 94.11354 | R72: =Q72*(1+R47) -> 95.995811 | S72: =R72*(1+S47) -> 97.915727 | ... AA72: =Z72*(1+AA47) -> 114.72388
B73: Other SG&A (Marketing, IT, etc) | D73: (EUR, mio) | H73: =H$34*Inputs!$L$21 -> 64.310001 | I73: =I$34*Inputs!$L$21 -> 79.652529 | J73: =J$34*Inputs!$L$21 -> 95.583035 | K73: =K$34*Inputs!$L$21 -> 165.57849 | L73: =L$34*Inputs!$L$21 -> 183.61194 | M73: =M$34*Inputs!$L$21 -> 202.27088 | N73: =N$34*Inputs!$L$21 -> 206.11403 | O73: =O$34*Inputs!$L$21 -> 209.82408 | ... AA73: =AA$34*Inputs!$L$21 -> 255.10279
B74: Subtotal | D74: (EUR, mio) | G74: =H74/$H$34 -> 0.065613435 | H74: =SUM(H72:H73) -> 120.56 | I74: =SUM(I72:I73) -> 137.02753 | J74: =SUM(J72:J73) -> 154.10554 | K74: =SUM(K72:K73) -> 249.14862 | L74: =SUM(L72:L73) -> 268.85347 | M74: =SUM(M72:M73) -> 289.21724 | N74: =SUM(N72:N73) -> 294.79932 | O74: =SUM(O72:O73) -> 300.28308 | ... AA74: =SUM(AA72:AA73) -> 369.82667
B76: R&D
B77: R&D Expenses | D77: (EUR, mio) | G77: =H77/$H$34 -> 0.02 | H77: =Inputs!$L$22*Model!H$34 -> 36.748572 | I77: =Inputs!$L$22*Model!I$34 -> 45.515731 | J77: =Inputs!$L$22*Model!J$34 -> 54.618877 | K77: =Inputs!$L$22*Model!K$34 -> 94.616281 | L77: =Inputs!$L$22*Model!L$34 -> 104.92111 | M77: =Inputs!$L$22*Model!M$34 -> 115.58336 | N77: =Inputs!$L$22*Model!N$34 -> 117.77944 | O77: =Inputs!$L$22*Model!O$34 -> 119.89947 | ... AA77: =Inputs!$L$22*Model!AA$34 -> 145.77302
B79: Total Operational Expenses | D79: (EUR, mio) | H79: =H74+H77 -> 157.30857 | I79: =I74+I77 -> 182.54326 | J79: =J74+J77 -> 208.72441 | K79: =K74+K77 -> 343.7649 | L79: =L74+L77 -> 373.77458 | M79: =M74+M77 -> 404.8006 | N79: =N74+N77 -> 412.57876 | O79: =O74+O77 -> 420.18255 | ... AA79: =AA74+AA77 -> 515.59969
B82: Income Statement
B84: All figures in EUR millions unless stated
B85: {=CONCATENATE("Model Drivers: ",INDEX(Inputs!$B$96:$B$98,Inputs!$D$86)," & ",INDEX(Inputs!$B$143:$B$144,Inputs!$D$139)," Financing")} -> Model Drivers: Base Case & Two Phased Financing | F85: 2025 | G85: 2026 | H85: =Inputs!$F$8 -> 2027 | I85: =H85+1 -> 2028 | J85: =I85+1 -> 2029 | K85: =J85+1 -> 2030 | L85: =K85+1 -> 2031 | M85: =L85+1 -> 2032 | N85: =M85+1 -> 2033 | O85: =N85+1 -> 2034 | P85: =O85+1 -> 2035 | ... AA85: =Z85+1 -> 2046
B88: Tax Rate | C88: =Inputs!$F$16 -> 0.206
B90: Revenue | H90: =H$34 -> 1837.4286 | I90: =I$34 -> 2275.7866 | J90: =J$34 -> 2730.9439 | K90: =K$34 -> 4730.8141 | L90: =L$34 -> 5246.0554 | M90: =M$34 -> 5779.168 | N90: =N$34 -> 5888.9722 | O90: =O$34 -> 5994.9737 | ... AA90: =AA$34 -> 7288.6511
B91: COGS | H91: =H66 -> 1237.6968 | I91: =I66 -> 1532.9759 | J91: =J66 -> 1839.5711 | K91: =K66 -> 3188.4283 | L91: =L66 -> 3537.6162 | M91: =M66 -> 3899.2434 | N91: =N66 -> 3975.5005 | O91: =O66 -> 4051.4893 | ... AA91: =AA66 -> 5044.2646
B92: Gross Profit | H92: =H90-H91 -> 599.73177 | I92: =I90-I91 -> 742.81064 | J92: =J90-J91 -> 891.37276 | K92: =K90-K91 -> 1542.3858 | L92: =L90-L91 -> 1708.4391 | M92: =M90-M91 -> 1879.9246 | N92: =N90-N91 -> 1913.4717 | O92: =O90-O91 -> 1943.4844 | ... AA92: =AA90-AA91 -> 2244.3865
B93: Gross Margin | H93: =H92/H90 -> 0.32639732 | I93: =I92/I90 -> 0.32639732 | J93: =J92/J90 -> 0.32639732 | K93: =K92/K90 -> 0.32602967 | L93: =L92/L90 -> 0.32566166 | M93: =M92/M90 -> 0.32529329 | N93: =N92/N90 -> 0.32492456 | O93: =O92/O90 -> 0.32418565 | ... AA93: =AA92/AA90 -> 0.30792892
B95: SG&A | H95: =H74 -> 120.56 | I95: =I74 -> 137.02753 | J95: =J74 -> 154.10554 | K95: =K74 -> 249.14862 | L95: =L74 -> 268.85347 | M95: =M74 -> 289.21724 | N95: =N74 -> 294.79932 | O95: =O74 -> 300.28308 | ... AA95: =AA74 -> 369.82667
B96: R&D | H96: =H77 -> 36.748572 | I96: =I77 -> 45.515731 | J96: =J77 -> 54.618877 | K96: =K77 -> 94.616281 | L96: =L77 -> 104.92111 | M96: =M77 -> 115.58336 | N96: =N77 -> 117.77944 | O96: =O77 -> 119.89947 | ... AA96: =AA77 -> 145.77302
B97: EBITDA | H97: =H92-H95-H96 -> 442.4232 | I97: =I92-I95-I96 -> 560.26738 | J97: =J92-J95-J96 -> 682.64835 | K97: =K92-K95-K96 -> 1198.6209 | L97: =L92-L95-L96 -> 1334.6645 | M97: =M92-M95-M96 -> 1475.124 | N97: =N92-N95-N96 -> 1500.893 | O97: =O92-O95-O96 -> 1523.3019 | ... AA97: =AA92-AA95-AA96 -> 1728.7868
B98: EBITDA Margin | H98: =H97/H90 -> 0.24078389 | I98: =I97/I90 -> 0.24618626 | J98: =J97/J90 -> 0.24996792 | K98: =K97/K90 -> 0.25336461 | L98: =L97/L90 -> 0.25441297 | M98: =M97/M90 -> 0.2552485 | N98: =N97/N90 -> 0.25486501 | O98: =O97/O90 -> 0.25409651 | ... AA98: =AA97/AA90 -> 0.23718885
B100: Depreciation | H100: =H$160 -> 150 | I100: =I$160 -> 150 | J100: =J$160 -> 150 | K100: =K$160 -> 275 | L100: =L$160 -> 275 | M100: =M$160 -> 275 | N100: =N$160 -> 275 | O100: =O$160 -> 275 | ... AA100: =AA$160 -> 275
B101: EBIT | H101: =H97-H100 -> 292.4232 | I101: =I97-I100 -> 410.26738 | J101: =J97-J100 -> 532.64835 | K101: =K97-K100 -> 923.62086 | L101: =L97-L100 -> 1059.6645 | M101: =M97-M100 -> 1200.124 | N101: =N97-N100 -> 1225.893 | O101: =O97-O100 -> 1248.3019 | ... AA101: =AA97-AA100 -> 1453.7868
B103: Interest | H103: =H$236 -> 108 | I103: =I$236 -> 102.6 | J103: =J$236 -> 97.2 | K103: =K$236 -> 181.8 | L103: =L$236 -> 171.10588 | M103: =M$236 -> 160.41176 | N103: =N$236 -> 149.71765 | O103: =O$236 -> 139.02353 | ... AA103: =AA$236 -> 10.694118
B104: EBT | H104: =H101-H103 -> 184.4232 | I104: =I101-I103 -> 307.66738 | J104: =J101-J103 -> 435.44835 | K104: =K101-K103 -> 741.82086 | L104: =L101-L103 -> 888.55866 | M104: =M101-M103 -> 1039.7122 | N104: =N101-N103 -> 1076.1753 | O104: =O101-O103 -> 1109.2784 | ... AA104: =AA101-AA103 -> 1443.0927
B106: Total Tax | H106: =MAX(H104*$C$88,0) -> 37.991179 | I106: =MAX(I104*$C$88,0) -> 63.379479 | J106: =MAX(J104*$C$88,0) -> 89.70236 | K106: =MAX(K104*$C$88,0) -> 152.8151 | L106: =MAX(L104*$C$88,0) -> 183.04308 | M106: =MAX(M104*$C$88,0) -> 214.18072 | N106: =MAX(N104*$C$88,0) -> 221.69211 | O106: =MAX(O104*$C$88,0) -> 228.51134 | ... AA106: =MAX(AA104*$C$88,0) -> 297.27709
B108: Net Income | H108: =H104-H106 -> 146.43202 | I108: =I104-I106 -> 244.2879 | J108: =J104-J106 -> 345.74599 | K108: =K104-K106 -> 589.00576 | L108: =L104-L106 -> 705.51558 | M108: =M104-M106 -> 825.53151 | N108: =N104-N106 -> 854.48319 | O108: =O104-O106 -> 880.76702 | ... AA108: =AA104-AA106 -> 1145.8156
B112: Working Capital Schedule
B114: All figures in EUR millions unless stated
B115: {=CONCATENATE("Model Drivers: ",INDEX(Inputs!$B$96:$B$98,Inputs!$D$86)," & ",INDEX(Inputs!$B$143:$B$144,Inputs!$D$139)," Financing")} -> Model Drivers: Base Case & Two Phased Financing | F115: 2025 | G115: 2026 | H115: =Inputs!$F$8 -> 2027 | I115: =H115+1 -> 2028 | J115: =I115+1 -> 2029 | K115: =J115+1 -> 2030 | L115: =K115+1 -> 2031 | M115: =L115+1 -> 2032 | N115: =M115+1 -> 2033 | O115: =N115+1 -> 2034 | P115: =O115+1 -> 2035 | ... AA115: =Z115+1 -> 2046
B117: Days in Period | H117: 365 | I117: 365 | J117: 365 | K117: 365 | L117: 365 | M117: 365 | N117: 365 | O117: 365 | P117: 365 | Q117: 365 | R117: 365 | S117: 365 | T117: 365 | U117: 365 | V117: 365 | W117: 365 | X117: 365 | Y117: 365 | Z117: 365 | AA117: 365
B118: Revenue | H118: =H$90 -> 1837.4286 | I118: =I$90 -> 2275.7866 | J118: =J$90 -> 2730.9439 | K118: =K$90 -> 4730.8141 | L118: =L$90 -> 5246.0554 | M118: =M$90 -> 5779.168 | N118: =N$90 -> 5888.9722 | O118: =O$90 -> 5994.9737 | ... AA118: =AA$90 -> 7288.6511
B119: COGS | H119: =H$91 -> 1237.6968 | I119: =I$91 -> 1532.9759 | J119: =J$91 -> 1839.5711 | K119: =K$91 -> 3188.4283 | L119: =L$91 -> 3537.6162 | M119: =M$91 -> 3899.2434 | N119: =N$91 -> 3975.5005 | O119: =O$91 -> 4051.4893 | ... AA119: =AA$91 -> 5044.2646
B122: AMOUNTS PER DAY 1
B123: Accounts Receivable | D123: (Days) | H123: =Inputs!H$130 -> 40 | I123: =Inputs!I$130 -> 40 | J123: =Inputs!J$130 -> 40 | K123: =Inputs!K$130 -> 40 | L123: =Inputs!L$130 -> 40 | M123: =Inputs!M$130 -> 40 | N123: =Inputs!N$130 -> 40 | O123: =Inputs!O$130 -> 40 | ... AA123: =Inputs!AA$130 -> 40
B124: Inventory | D124: (Days) | H124: =Inputs!H$131 -> 50 | I124: =Inputs!I$131 -> 50 | J124: =Inputs!J$131 -> 50 | K124: =Inputs!K$131 -> 50 | L124: =Inputs!L$131 -> 50 | M124: =Inputs!M$131 -> 50 | N124: =Inputs!N$131 -> 50 | O124: =Inputs!O$131 -> 50 | ... AA124: =Inputs!AA$131 -> 50
B125: Accounts Payable | D125: (Days) | H125: =Inputs!H$132 -> 60 | I125: =Inputs!I$132 -> 60 | J125: =Inputs!J$132 -> 60 | K125: =Inputs!K$132 -> 60 | L125: =Inputs!L$132 -> 60 | M125: =Inputs!M$132 -> 60 | N125: =Inputs!N$132 -> 60 | O125: =Inputs!O$132 -> 60 | ... AA125: =Inputs!AA$132 -> 60
B128: TOTAL AMOUNTS
B129: Accounts Receivable | H129: =(H123/H$117)*H118 -> 201.36204 | I129: =(I123/I$117)*I118 -> 249.40127 | J129: =(J123/J$117)*J118 -> 299.28152 | K129: =(K123/K$117)*K118 -> 518.44538 | L129: =(L123/L$117)*L118 -> 574.91018 | M129: =(M123/M$117)*M118 -> 633.33348 | N129: =(N123/N$117)*N118 -> 645.36682 | O129: =(O123/O$117)*O118 -> 656.98342 | ... AA129: =(AA123/AA$117)*AA118 -> 798.75629
B130: Inventory | H130: =(H124/H$117)*H119 -> 169.54751 | I130: =(I124/I$117)*I119 -> 209.9967 | J130: =(J124/J$117)*J119 -> 251.99604 | K130: =(K124/K$117)*K119 -> 436.771 | L130: =(L124/L$117)*L119 -> 484.60497 | M130: =(M124/M$117)*M119 -> 534.14293 | N130: =(N124/N$117)*N119 -> 544.58911 | O130: =(O124/O$117)*O119 -> 554.99853 | ... AA130: =(AA124/AA$117)*AA119 -> 690.99516
B131: Accounts Payable | H131: =(H125/H$117)*H119 -> 203.45701 | I131: =(I125/I$117)*I119 -> 251.99604 | J131: =(J125/J$117)*J119 -> 302.39525 | K131: =(K125/K$117)*K119 -> 524.1252 | L131: =(L125/L$117)*L119 -> 581.52596 | M131: =(M125/M$117)*M119 -> 640.97152 | N131: =(N125/N$117)*N119 -> 653.50693 | O131: =(O125/O$117)*O119 -> 665.99824 | ... AA131: =(AA125/AA$117)*AA119 -> 829.19419
B134: NET WORKING CAPITAL
B135: Current Assets | H135: =SUM(H129:H130) -> 370.90955 | I135: =SUM(I129:I130) -> 459.39797 | J135: =SUM(J129:J130) -> 551.27756 | K135: =SUM(K129:K130) -> 955.21638 | L135: =SUM(L129:L130) -> 1059.5151 | M135: =SUM(M129:M130) -> 1167.4764 | N135: =SUM(N129:N130) -> 1189.9559 | O135: =SUM(O129:O130) -> 1211.982 | ... AA135: =SUM(AA129:AA130) -> 1489.7514
B136: Current Liabilities | H136: =SUM(H131) -> 203.45701 | I136: =SUM(I131) -> 251.99604 | J136: =SUM(J131) -> 302.39525 | K136: =SUM(K131) -> 524.1252 | L136: =SUM(L131) -> 581.52596 | M136: =SUM(M131) -> 640.97152 | N136: =SUM(N131) -> 653.50693 | O136: =SUM(O131) -> 665.99824 | ... AA136: =SUM(AA131) -> 829.19419
B137: Net Working Capital | G137: 150 | H137: =H135-H136 -> 167.45254 | I137: =I135-I136 -> 207.40193 | J137: =J135-J136 -> 248.88231 | K137: =K135-K136 -> 431.09118 | L137: =L135-L136 -> 477.98918 | M137: =M135-M136 -> 526.50489 | N137: =N135-N136 -> 536.449 | O137: =O135-O136 -> 545.98371 | ... AA137: =AA135-AA136 -> 660.55726
B140: Cash from Working Capital Items | H140: =G137-H137 -> -17.452535 | I140: =H137-I137 -> -39.949391 | J140: =I137-J137 -> -41.480385 | K140: =J137-K137 -> -182.20887 | L140: =K137-L137 -> -46.898008 | M140: =L137-M137 -> -48.515711 | N140: =M137-N137 -> -9.9441012 | O140: =N137-O137 -> -9.5347186 | ... AA140: =Z137-AA137 -> -10.099488
B144: Capex & Depreciation Schedule
B146: All figures in EUR millions unless stated
B147: {=CONCATENATE("Model Drivers: ",INDEX(Inputs!$B$96:$B$98,Inputs!$D$86)," & ",INDEX(Inputs!$B$143:$B$144,Inputs!$D$139)," Financing")} -> Model Drivers: Base Case & Two Phased Financing | F147: 2025 | G147: 2026 | H147: =Inputs!$F$8 -> 2027 | I147: =H147+1 -> 2028 | J147: =I147+1 -> 2029 | K147: =J147+1 -> 2030 | L147: =K147+1 -> 2031 | M147: =L147+1 -> 2032 | N147: =M147+1 -> 2033 | O147: =N147+1 -> 2034 | P147: =O147+1 -> 2035 | ... AA147: =Z147+1 -> 2046
B150: Construction Capex | F150: =Inputs!F$141 -> 1500 | G150: =Inputs!G$141 -> 1500 | H150: =Inputs!H$141 -> 1000 | I150: =Inputs!I$141 -> 1000 | J150: =Inputs!J$141 -> 500 | K150: =Inputs!K$141 -> 0 | L150: =Inputs!L$141 -> 0 | M150: =Inputs!M$141 -> 0 | ... AA150: =Inputs!AA$141 -> 0
B151: Maintenance Capex | F151: 0 | G151: 0 | H151: =H90*1% -> 18.374286 | I151: =I90*1% -> 22.757866 | J151: =J90*1% -> 27.309439 | K151: =K90*1% -> 47.308141 | L151: =L90*1% -> 52.460554 | M151: =M90*1% -> 57.79168 | N151: =N90*1% -> 58.889722 | O151: =O90*1% -> 59.949737 | ... AA151: =AA90*1% -> 72.886511
B152: Total Capex | F152: =F150+F151 -> 1500 | G152: =G150+G151 -> 1500 | H152: =H150+H151 -> 1018.3743 | I152: =I150+I151 -> 1022.7579 | J152: =J150+J151 -> 527.30944 | K152: =K150+K151 -> 47.308141 | L152: =L150+L151 -> 52.460554 | M152: =M150+M151 -> 57.79168 | ... AA152: =AA150+AA151 -> 72.886511
...
